knowledge_stack/__init__.py
knowledge_stack/api_client.py
knowledge_stack/api_response.py
knowledge_stack/configuration.py
knowledge_stack/exceptions.py
knowledge_stack/py.typed
knowledge_stack/rest.py
knowledge_stack/api/__init__.py
knowledge_stack/api/admin_api.py
knowledge_stack/api/agent_participants_api.py
knowledge_stack/api/auth_api.py
knowledge_stack/api/chunks_api.py
knowledge_stack/api/default_api.py
knowledge_stack/api/document_tags_api.py
knowledge_stack/api/documents_api.py
knowledge_stack/api/folder_tags_api.py
knowledge_stack/api/folders_api.py
knowledge_stack/api/invite_api.py
knowledge_stack/api/jobs_api.py
knowledge_stack/api/organization_api.py
knowledge_stack/api/query_api.py
knowledge_stack/api/search_api.py
knowledge_stack/api/tenant_tags_api.py
knowledge_stack/api/tenant_threads_api.py
knowledge_stack/api/thread_turns_api.py
knowledge_stack/api/user_participants_api.py
knowledge_stack/models/__init__.py
knowledge_stack/models/base_participant.py
knowledge_stack/models/base_resp_delete.py
knowledge_stack/models/category.py
knowledge_stack/models/chunk_lineage.py
knowledge_stack/models/chunk_type.py
knowledge_stack/models/citation_item.py
knowledge_stack/models/document_processing_status.py
knowledge_stack/models/document_version_metadata.py
knowledge_stack/models/http_validation_error.py
knowledge_stack/models/image_category.py
knowledge_stack/models/invite_status.py
knowledge_stack/models/job_status_input.py
knowledge_stack/models/job_status_output.py
knowledge_stack/models/job_type.py
knowledge_stack/models/ks_auth_provider_type.py
knowledge_stack/models/ksidp_pw_user_create_request.py
knowledge_stack/models/ksidp_pw_user_signin_request.py
knowledge_stack/models/list_folder_content_type.py
knowledge_stack/models/paginated_response_resp_chunk.py
knowledge_stack/models/paginated_response_resp_complete_tag.py
knowledge_stack/models/paginated_response_resp_document.py
knowledge_stack/models/paginated_response_resp_document_tag.py
knowledge_stack-0.9.2.dist-info/METADATA
knowledge_stack-0.9.2.dist-info/WHEEL
knowledge_stack-0.9.2.dist-info/top_level.txt
knowledge_stack-0.9.2.dist-info/RECORD
